examples/__init__.py
examples/all_of_column_models.py
examples/all_of_model_models.py
examples/ref_column_models.py
examples/ref_model_models.py
examples/relationship_many_to_one_backref_models.py
examples/relationship_many_to_one_backref_models_traditional.py
examples/relationship_many_to_one_models.py
examples/relationship_many_to_one_models_traditional.py
examples/simple_models.py
examples/app/__init__.py
examples/app/api.py
examples/app/app.py
examples/app/models.py
openapi_sqlalchemy/__init__.py
openapi_sqlalchemy/column_factory.py
openapi_sqlalchemy/exceptions.py
openapi_sqlalchemy/model_factory.py
openapi_sqlalchemy/types.py
openapi_sqlalchemy/helpers/__init__.py
openapi_sqlalchemy/helpers/add_logical_name.py
openapi_sqlalchemy/helpers/merge_all_of.py
openapi_sqlalchemy/helpers/peek_type.py
openapi_sqlalchemy/helpers/prepare_schema.py
openapi_sqlalchemy/helpers/prepare_spec.py
openapi_sqlalchemy/helpers/resolve_ref.py
openapi_sqlalchemy/helpers/testing_guard.py
openapi_sqlalchemy/helpers/get_ext_prop/__init__.py
tests/__init__.py
tests/conftest.py
tests/test_column_factory.py
tests/test_integration.py
tests/test_model_factory.py
tests/examples/__init__.py
tests/examples/app/__init__.py
tests/examples/app/conftest.py
tests/examples/app/test_app.py
tests/openapi_sqlalchemy/__init__.py
tests/openapi_sqlalchemy/conftest.py
tests/openapi_sqlalchemy/test_column_factory.py
tests/openapi_sqlalchemy/test_integration.py
tests/openapi_sqlalchemy/test_model_factory.py
OpenAPI_SQLAlchemy-0.7.0.dist-info/LICENSE
OpenAPI_SQLAlchemy-0.7.0.dist-info/METADATA
OpenAPI_SQLAlchemy-0.7.0.dist-info/WHEEL
OpenAPI_SQLAlchemy-0.7.0.dist-info/top_level.txt
OpenAPI_SQLAlchemy-0.7.0.dist-info/RECORD
