Metadata-Version: 2.1
Name: OpenAPI-SQLAlchemy
Version: 0.7.0
Summary: Maps an OpenAPI schema to SQLAlchemy models.
Home-page: https://github.com/jdkandersson/OpenAPI-SQLAlchemy
Author: David Andersson
Author-email: anderssonpublic@gmail.com
License: UNKNOWN
Platform: UNKNOWN
Classifier: Programming Language :: Python :: 3
Classifier: Programming Language :: Python :: 3.6
Classifier: Programming Language :: Python :: 3.7
Classifier: Programming Language :: Python :: 3.8
Classifier: License :: OSI Approved :: Apache Software License
Classifier: Operating System :: OS Independent
Classifier: Development Status :: 3 - Alpha
Classifier: Natural Language :: English
Classifier: Topic :: Database
Requires-Python: >=3.6
Requires-Dist: SQLAlchemy (>=1.0)
Requires-Dist: typing-extensions (>=3.5)
Requires-Dist: jsonschema (>=3)
Provides-Extra: dev
Requires-Dist: pytest ; extra == 'dev'
Requires-Dist: tox ; extra == 'dev'
Requires-Dist: tox-pyenv ; extra == 'dev'
Requires-Dist: pylint ; extra == 'dev'
Requires-Dist: pytest-cov ; extra == 'dev'
Requires-Dist: pytest-flakes ; extra == 'dev'
Requires-Dist: pytest-flask ; extra == 'dev'
Requires-Dist: pytest-flask-sqlalchemy ; extra == 'dev'
Requires-Dist: mypy ; extra == 'dev'
Requires-Dist: pydocstyle ; extra == 'dev'
Requires-Dist: black ; extra == 'dev'
Requires-Dist: pre-commit ; extra == 'dev'
Requires-Dist: isort ; extra == 'dev'
Requires-Dist: PyYAML ; extra == 'dev'
Requires-Dist: Sphinx ; extra == 'dev'
Requires-Dist: doc8 ; extra == 'dev'
Requires-Dist: connexion[swagger-ui] ; extra == 'dev'
Requires-Dist: Flask-SQLAlchemy ; extra == 'dev'
